batch_operation_of_files/config.json
batch_operation_of_files/main.py
batch_operation_of_files-0.0.0.dist-info/LICENSE
batch_operation_of_files-0.0.0.dist-info/METADATA
batch_operation_of_files-0.0.0.dist-info/WHEEL
batch_operation_of_files-0.0.0.dist-info/RECORD
