Metadata-Version: 2.1
Name: batch-operation-of-files
Version: 0.0.0
Summary:  文件的批量移动复制删除，可指定文件夹可操作层数与最大输出位置层数
License: MIT
Author: ziru-w
Author-email: 77319678+ziru-w@users.noreply.github.com
Requires-Python: >=3.6,<4.0
Classifier: License :: OSI Approved :: MIT License
Classifier: Programming Language :: Python :: 3
Classifier: Programming Language :: Python :: 3.6
Classifier: Programming Language :: Python :: 3.7
Classifier: Programming Language :: Python :: 3.8
Classifier: Programming Language :: Python :: 3.9
Classifier: Programming Language :: Python :: 3.10
Classifier: Programming Language :: Python :: 3.11
